{
  "accountName": "",
  "sharedSecret": "",
  "games": [
    {
      "appId": 221410,
      "name": "Steam for Linux"
    },
    {
      "appId": 730,
      "name": "CS2"
    },
    {
      "appId": 526870,
      "name": "Satisfactory"
    },
    {
      "appId": 359550,
      "name": "Rainbow Six"
    },
    {
      "appId": 1118310,
      "name": "RetroArch"
    },
    {
      "appId": 493520,
      "name": "GTFO"
    },
    {
      "appId": 271590,
      "name": "GTA V"
    },
    {
      "appId": 1905180,
      "name": "OBS Studio"
    },
    {
      "appId": 2200,
      "name": "Q3 Arena"
    },
    {
      "appId": 227940,
      "name": "Heroes & Generals"
    },
    {
      "appId": 1326470,
      "name": "Sons of the Forest"
    },
    {
      "appId": 1468260,
      "name": "Leaf Blower Revolution"
    },
    {
      "appId": 3241660,
      "name": "REPO"
    }
  ],
  "rememberPassword": true,
  "password": "",
  "name": "pilot2254"
}